{
  "title": "Pessoas de 15 anos ou mais alfabetizadas",
  "subtitle": "Total de pessoas na condição e total de pessoas no município.",
  "unit": "pessoas",
  "calculation": {
    "numerator_label": "Pessoas de 15 anos ou mais alfabetizadas",
    "denominator_label": "População de 15 anos ou mais"
  },
  "series_total": [
    {
      "ano": 2010,
      "valor": 6162
    },
    {
      "ano": 2022,
      "valor": 8061
    }
  ],
  "series_components": [
    {
      "ano": 2010,
      "numerador": 6162,
      "denominador": 6519,
      "percentual": 94.5
    },
    {
      "ano": 2022,
      "numerador": 8061,
      "denominador": 8440,
      "percentual": 95.5
    }
  ]
}
