{
  "schemaVersion": "municipal-education-overview-v1",
  "publicationState": "published",
  "municipality": {
    "idMunicipality": "4318002",
    "name": "São Borja",
    "slug": "sao-borja"
  },
  "reference": {
    "year": 2025,
    "generatedAt": "2026-07-22T19:11:38-03:00"
  },
  "universe": {
    "territorialBasis": "school_location",
    "locationLabel": "Localização da escola",
    "basicEducationSourceField": "QT_MAT_BAS",
    "methodologyNotes": [
      "O snapshot usa exclusivamente o ano de 2025; não há seleção dinâmica nem fallback anual.",
      "Educação Básica usa QT_MAT_BAS como total oficial e não é recomposta pela soma das etapas.",
      "A base territorial é o município onde a escola está localizada; urbana e rural referem-se à localização da escola.",
      "Subtotais públicos só são derivados quando municipal, estadual e federal estão observados ou com zero derivado; ausências não confirmadas permanecem indisponíveis.",
      "Linhas com os sete campos centrais nulos não aumentam totais e mantêm indisponível apenas o recorte de rede/localização afetado.",
      "Zero derivado exige carga municipal completa de 2025, domínios válidos, ausência de duplicidade/negativos, total da etapa observado e ausência de nullCoreRow no recorte.",
      "Os cinco componentes principais da composição reconciliam com QT_MAT_BAS; detalhamentos internos não são somados novamente.",
      "A Educação Especial é um recorte transversal já incluído nas etapas e modalidades da Educação Básica.",
      "As taxas de rendimento usam os registros municipais do INEP para o conjunto das redes, sem média entre escolas ou dependências."
    ]
  },
  "basicEducation": {
    "total": {
      "value": 11081,
      "state": "observed",
      "year": 2025,
      "sourceId": "inep_censo_escolar",
      "sourceField": "QT_MAT_BAS"
    }
  },
  "basicEducationComposition": {
    "total": {
      "value": 11081,
      "state": "observed",
      "year": 2025,
      "sourceId": "inep_censo_escolar",
      "sourceField": "QT_MAT_BAS"
    },
    "components": {
      "earlyChildhood": {
        "total": {
          "value": 2280,
          "state": "observed",
          "year": 2025,
          "sourceId": "inep_censo_escolar",
          "sourceField": "QT_MAT_INF"
        },
        "details": {
          "creche": {
            "value": 940,
            "state": "observed",
            "year": 2025,
            "sourceId": "inep_censo_escolar",
            "sourceField": "QT_MAT_INF_CRE"
          },
          "preSchool": {
            "value": 1340,
            "state": "observed",
            "year": 2025,
            "sourceId": "inep_censo_escolar",
            "sourceField": "QT_MAT_INF_PRE"
          }
        }
      },
      "elementary": {
        "total": {
          "value": 6452,
          "state": "observed",
          "year": 2025,
          "sourceId": "inep_censo_escolar",
          "sourceField": "QT_MAT_FUND"
        },
        "details": {
          "initialYears": {
            "value": 3693,
            "state": "observed",
            "year": 2025,
            "sourceId": "inep_censo_escolar",
            "sourceField": "QT_MAT_FUND_AI"
          },
          "finalYears": {
            "value": 2759,
            "state": "observed",
            "year": 2025,
            "sourceId": "inep_censo_escolar",
            "sourceField": "QT_MAT_FUND_AF"
          }
        }
      },
      "highSchool": {
        "total": {
          "value": 1746,
          "state": "observed",
          "year": 2025,
          "sourceId": "inep_censo_escolar",
          "sourceField": "QT_MAT_MED"
        },
        "details": {
          "integratedTechnical": {
            "value": 390,
            "state": "observed",
            "year": 2025,
            "sourceId": "inep_censo_escolar",
            "sourceField": "QT_MAT_MED_IFTP_CT"
          }
        }
      },
      "youthAndAdultEducation": {
        "total": {
          "value": 390,
          "state": "observed",
          "year": 2025,
          "sourceId": "inep_censo_escolar",
          "sourceField": "QT_MAT_EJA"
        },
        "details": {
          "elementary": {
            "value": 193,
            "state": "observed",
            "year": 2025,
            "sourceId": "inep_censo_escolar",
            "sourceField": "QT_MAT_EJA_FUND"
          },
          "highSchool": {
            "value": 197,
            "state": "observed",
            "year": 2025,
            "sourceId": "inep_censo_escolar",
            "sourceField": "QT_MAT_EJA_MED"
          }
        }
      },
      "otherProfessionalOffers": {
        "total": {
          "value": 213,
          "state": "observed",
          "year": 2025,
          "sourceId": "inep_censo_escolar",
          "sourceField": "derived:QT_MAT_PROF_TEC_CONC+QT_MAT_PROF_TEC_SUBS+QT_MAT_PROF_TEC_IFTP_CT+QT_MAT_PROF_IFTP_QP+QT_MAT_PROF_FIC_CONC"
        },
        "details": {
          "concomitantTechnical": {
            "value": 34,
            "state": "observed",
            "year": 2025,
            "sourceId": "inep_censo_escolar",
            "sourceField": "QT_MAT_PROF_TEC_CONC"
          },
          "subsequentTechnical": {
            "value": 179,
            "state": "observed",
            "year": 2025,
            "sourceId": "inep_censo_escolar",
            "sourceField": "QT_MAT_PROF_TEC_SUBS"
          },
          "otherOffers": {
            "value": 0,
            "state": "observed",
            "year": 2025,
            "sourceId": "inep_censo_escolar",
            "sourceField": "derived:QT_MAT_PROF_TEC_IFTP_CT+QT_MAT_PROF_IFTP_QP+QT_MAT_PROF_FIC_CONC"
          }
        }
      }
    },
    "reconciliation": {
      "id": "basic_education_composition",
      "label": "Cinco componentes aditivos = Educação Básica",
      "expected": 11081,
      "observed": 11081,
      "difference": 0,
      "status": "reconciled"
    }
  },
  "specialEducation": {
    "total": {
      "value": 962,
      "state": "observed",
      "year": 2025,
      "sourceId": "inep_censo_escolar",
      "sourceField": "QT_MAT_ESP"
    },
    "commonClasses": {
      "value": 881,
      "state": "observed",
      "year": 2025,
      "sourceId": "inep_censo_escolar",
      "sourceField": "QT_MAT_ESP_CC"
    },
    "exclusiveClasses": {
      "value": 81,
      "state": "observed",
      "year": 2025,
      "sourceId": "inep_censo_escolar",
      "sourceField": "QT_MAT_ESP_CE"
    }
  },
  "highSchool": {
    "total": {
      "total": {
        "value": 1746,
        "state": "observed",
        "year": 2025,
        "sourceId": "inep_censo_escolar",
        "sourceField": "QT_MAT_MED"
      },
      "shareOfBasicEducation": {
        "value": 15.756700658785308,
        "numerator": 1746,
        "denominator": 11081,
        "state": "observed",
        "year": 2025,
        "sourceId": "inep_censo_escolar"
      },
      "byNetwork": {
        "publicSubtotal": {
          "enrollments": {
            "value": 1665,
            "state": "observed",
            "year": 2025,
            "sourceId": "inep_censo_escolar",
            "sourceField": "derived:municipal+estadual+federal"
          },
          "share": {
            "value": 95.36082474226805,
            "numerator": 1665,
            "denominator": 1746,
            "state": "observed",
            "year": 2025,
            "sourceId": "inep_censo_escolar"
          }
        },
        "municipal": {
          "enrollments": {
            "value": 0,
            "state": "derived_zero",
            "year": 2025,
            "sourceId": "inep_censo_escolar",
            "sourceField": "QT_MAT_MED"
          },
          "share": {
            "value": 0.0,
            "numerator": 0,
            "denominator": 1746,
            "state": "derived_zero",
            "year": 2025,
            "sourceId": "inep_censo_escolar"
          }
        },
        "state": {
          "enrollments": {
            "value": 1275,
            "state": "observed",
            "year": 2025,
            "sourceId": "inep_censo_escolar",
            "sourceField": "QT_MAT_MED"
          },
          "share": {
            "value": 73.02405498281786,
            "numerator": 1275,
            "denominator": 1746,
            "state": "observed",
            "year": 2025,
            "sourceId": "inep_censo_escolar"
          }
        },
        "federal": {
          "enrollments": {
            "value": 390,
            "state": "observed",
            "year": 2025,
            "sourceId": "inep_censo_escolar",
            "sourceField": "QT_MAT_MED"
          },
          "share": {
            "value": 22.336769759450174,
            "numerator": 390,
            "denominator": 1746,
            "state": "observed",
            "year": 2025,
            "sourceId": "inep_censo_escolar"
          }
        },
        "private": {
          "enrollments": {
            "value": 81,
            "state": "observed",
            "year": 2025,
            "sourceId": "inep_censo_escolar",
            "sourceField": "QT_MAT_MED"
          },
          "share": {
            "value": 4.639175257731959,
            "numerator": 81,
            "denominator": 1746,
            "state": "observed",
            "year": 2025,
            "sourceId": "inep_censo_escolar"
          }
        }
      },
      "bySchoolLocation": {
        "urban": {
          "enrollments": {
            "value": 1685,
            "state": "observed",
            "year": 2025,
            "sourceId": "inep_censo_escolar",
            "sourceField": "QT_MAT_MED"
          },
          "share": {
            "value": 96.50630011454754,
            "numerator": 1685,
            "denominator": 1746,
            "state": "observed",
            "year": 2025,
            "sourceId": "inep_censo_escolar"
          }
        },
        "rural": {
          "enrollments": {
            "value": 61,
            "state": "observed",
            "year": 2025,
            "sourceId": "inep_censo_escolar",
            "sourceField": "QT_MAT_MED"
          },
          "share": {
            "value": 3.493699885452463,
            "numerator": 61,
            "denominator": 1746,
            "state": "observed",
            "year": 2025,
            "sourceId": "inep_censo_escolar"
          }
        }
      }
    },
    "integratedTechnical": {
      "total": {
        "value": 390,
        "state": "observed",
        "year": 2025,
        "sourceId": "inep_censo_escolar",
        "sourceField": "QT_MAT_MED_IFTP_CT"
      },
      "shareOfHighSchool": {
        "value": 22.336769759450174,
        "numerator": 390,
        "denominator": 1746,
        "state": "observed",
        "year": 2025,
        "sourceId": "inep_censo_escolar"
      }
    }
  },
  "schoolPerformance": {
    "referenceYear": 2025,
    "stages": {
      "elementary": {
        "approval": {
          "value": 98.8,
          "state": "observed",
          "year": 2025,
          "sourceId": "inep_taxas_rendimento_escolar",
          "sourceField": "taxa_aprovacao"
        },
        "failure": {
          "value": 1,
          "state": "observed",
          "year": 2025,
          "sourceId": "inep_taxas_rendimento_escolar",
          "sourceField": "taxa_reprovacao"
        },
        "dropout": {
          "value": 0.2,
          "state": "observed",
          "year": 2025,
          "sourceId": "inep_taxas_rendimento_escolar",
          "sourceField": "taxa_abandono"
        }
      },
      "initialYears": {
        "approval": {
          "value": 98.9,
          "state": "observed",
          "year": 2025,
          "sourceId": "inep_taxas_rendimento_escolar",
          "sourceField": "taxa_aprovacao"
        },
        "failure": {
          "value": 1.1,
          "state": "observed",
          "year": 2025,
          "sourceId": "inep_taxas_rendimento_escolar",
          "sourceField": "taxa_reprovacao"
        },
        "dropout": {
          "value": 0,
          "state": "observed",
          "year": 2025,
          "sourceId": "inep_taxas_rendimento_escolar",
          "sourceField": "taxa_abandono"
        }
      },
      "finalYears": {
        "approval": {
          "value": 98.6,
          "state": "observed",
          "year": 2025,
          "sourceId": "inep_taxas_rendimento_escolar",
          "sourceField": "taxa_aprovacao"
        },
        "failure": {
          "value": 1,
          "state": "observed",
          "year": 2025,
          "sourceId": "inep_taxas_rendimento_escolar",
          "sourceField": "taxa_reprovacao"
        },
        "dropout": {
          "value": 0.4,
          "state": "observed",
          "year": 2025,
          "sourceId": "inep_taxas_rendimento_escolar",
          "sourceField": "taxa_abandono"
        }
      },
      "highSchool": {
        "approval": {
          "value": 97.2,
          "state": "observed",
          "year": 2025,
          "sourceId": "inep_taxas_rendimento_escolar",
          "sourceField": "taxa_aprovacao"
        },
        "failure": {
          "value": 2.6,
          "state": "observed",
          "year": 2025,
          "sourceId": "inep_taxas_rendimento_escolar",
          "sourceField": "taxa_reprovacao"
        },
        "dropout": {
          "value": 0.2,
          "state": "observed",
          "year": 2025,
          "sourceId": "inep_taxas_rendimento_escolar",
          "sourceField": "taxa_abandono"
        }
      }
    },
    "sourceId": "inep_taxas_rendimento_escolar"
  },
  "enrollmentComparison": {
    "years": [
      2015,
      2025
    ],
    "stages": {
      "basicEducation": {
        "total": {
          "value2015": {
            "value": 14308,
            "state": "observed",
            "year": 2015,
            "sourceId": "inep_censo_escolar",
            "sourceField": "QT_MAT_BAS"
          },
          "value2025": {
            "value": 11081,
            "state": "observed",
            "year": 2025,
            "sourceId": "inep_censo_escolar",
            "sourceField": "QT_MAT_BAS"
          },
          "absoluteChange": -3227,
          "percentageChange": {
            "value": -22.55381604696673,
            "numerator": -3227,
            "denominator": 14308,
            "state": "observed",
            "year": 2025,
            "sourceId": "inep_censo_escolar"
          }
        }
      },
      "earlyChildhood": {
        "total": {
          "value2015": {
            "value": 2000,
            "state": "observed",
            "year": 2015,
            "sourceId": "inep_censo_escolar",
            "sourceField": "QT_MAT_INF"
          },
          "value2025": {
            "value": 2280,
            "state": "observed",
            "year": 2025,
            "sourceId": "inep_censo_escolar",
            "sourceField": "QT_MAT_INF"
          },
          "absoluteChange": 280,
          "percentageChange": {
            "value": 14.000000000000002,
            "numerator": 280,
            "denominator": 2000,
            "state": "observed",
            "year": 2025,
            "sourceId": "inep_censo_escolar"
          }
        },
        "byNetwork": {
          "publicSubtotal": {
            "value2015": {
              "value": 1592,
              "state": "observed",
              "year": 2015,
              "sourceId": "inep_censo_escolar",
              "sourceField": "derived:municipal+estadual+federal"
            },
            "value2025": {
              "value": 2080,
              "state": "observed",
              "year": 2025,
              "sourceId": "inep_censo_escolar",
              "sourceField": "derived:municipal+estadual+federal"
            },
            "absoluteChange": 488,
            "percentageChange": {
              "value": 30.65326633165829,
              "numerator": 488,
              "denominator": 1592,
              "state": "observed",
              "year": 2025,
              "sourceId": "inep_censo_escolar"
            }
          },
          "municipal": {
            "value2015": {
              "value": 1494,
              "state": "observed",
              "year": 2015,
              "sourceId": "inep_censo_escolar",
              "sourceField": "QT_MAT_INF"
            },
            "value2025": {
              "value": 2080,
              "state": "observed",
              "year": 2025,
              "sourceId": "inep_censo_escolar",
              "sourceField": "QT_MAT_INF"
            },
            "absoluteChange": 586,
            "percentageChange": {
              "value": 39.223560910307896,
              "numerator": 586,
              "denominator": 1494,
              "state": "observed",
              "year": 2025,
              "sourceId": "inep_censo_escolar"
            }
          },
          "state": {
            "value2015": {
              "value": 98,
              "state": "observed",
              "year": 2015,
              "sourceId": "inep_censo_escolar",
              "sourceField": "QT_MAT_INF"
            },
            "value2025": {
              "value": 0,
              "state": "derived_zero",
              "year": 2025,
              "sourceId": "inep_censo_escolar",
              "sourceField": "QT_MAT_INF"
            },
            "absoluteChange": -98,
            "percentageChange": {
              "value": -100.0,
              "numerator": -98,
              "denominator": 98,
              "state": "observed",
              "year": 2025,
              "sourceId": "inep_censo_escolar"
            }
          },
          "federal": {
            "value2015": {
              "value": 0,
              "state": "derived_zero",
              "year": 2015,
              "sourceId": "inep_censo_escolar",
              "sourceField": "QT_MAT_INF"
            },
            "value2025": {
              "value": 0,
              "state": "derived_zero",
              "year": 2025,
              "sourceId": "inep_censo_escolar",
              "sourceField": "QT_MAT_INF"
            },
            "absoluteChange": 0,
            "percentageChange": {
              "value": null,
              "numerator": 0,
              "denominator": 0,
              "state": "not_applicable",
              "year": 2025,
              "sourceId": "inep_censo_escolar"
            }
          },
          "private": {
            "value2015": {
              "value": 408,
              "state": "observed",
              "year": 2015,
              "sourceId": "inep_censo_escolar",
              "sourceField": "QT_MAT_INF"
            },
            "value2025": {
              "value": 200,
              "state": "observed",
              "year": 2025,
              "sourceId": "inep_censo_escolar",
              "sourceField": "QT_MAT_INF"
            },
            "absoluteChange": -208,
            "percentageChange": {
              "value": -50.98039215686274,
              "numerator": -208,
              "denominator": 408,
              "state": "observed",
              "year": 2025,
              "sourceId": "inep_censo_escolar"
            }
          }
        },
        "bySchoolLocation": {
          "urban": {
            "value2015": {
              "value": 1919,
              "state": "observed",
              "year": 2015,
              "sourceId": "inep_censo_escolar",
              "sourceField": "QT_MAT_INF"
            },
            "value2025": {
              "value": 2170,
              "state": "observed",
              "year": 2025,
              "sourceId": "inep_censo_escolar",
              "sourceField": "QT_MAT_INF"
            },
            "absoluteChange": 251,
            "percentageChange": {
              "value": 13.079729025534132,
              "numerator": 251,
              "denominator": 1919,
              "state": "observed",
              "year": 2025,
              "sourceId": "inep_censo_escolar"
            }
          },
          "rural": {
            "value2015": {
              "value": 81,
              "state": "observed",
              "year": 2015,
              "sourceId": "inep_censo_escolar",
              "sourceField": "QT_MAT_INF"
            },
            "value2025": {
              "value": 110,
              "state": "observed",
              "year": 2025,
              "sourceId": "inep_censo_escolar",
              "sourceField": "QT_MAT_INF"
            },
            "absoluteChange": 29,
            "percentageChange": {
              "value": 35.80246913580247,
              "numerator": 29,
              "denominator": 81,
              "state": "observed",
              "year": 2025,
              "sourceId": "inep_censo_escolar"
            }
          }
        }
      },
      "creche": {
        "total": {
          "value2015": {
            "value": 755,
            "state": "observed",
            "year": 2015,
            "sourceId": "inep_censo_escolar",
            "sourceField": "QT_MAT_INF_CRE"
          },
          "value2025": {
            "value": 940,
            "state": "observed",
            "year": 2025,
            "sourceId": "inep_censo_escolar",
            "sourceField": "QT_MAT_INF_CRE"
          },
          "absoluteChange": 185,
          "percentageChange": {
            "value": 24.503311258278146,
            "numerator": 185,
            "denominator": 755,
            "state": "observed",
            "year": 2025,
            "sourceId": "inep_censo_escolar"
          }
        },
        "byNetwork": {
          "publicSubtotal": {
            "value2015": {
              "value": 523,
              "state": "observed",
              "year": 2015,
              "sourceId": "inep_censo_escolar",
              "sourceField": "derived:municipal+estadual+federal"
            },
            "value2025": {
              "value": 860,
              "state": "observed",
              "year": 2025,
              "sourceId": "inep_censo_escolar",
              "sourceField": "derived:municipal+estadual+federal"
            },
            "absoluteChange": 337,
            "percentageChange": {
              "value": 64.43594646271511,
              "numerator": 337,
              "denominator": 523,
              "state": "observed",
              "year": 2025,
              "sourceId": "inep_censo_escolar"
            }
          },
          "municipal": {
            "value2015": {
              "value": 523,
              "state": "observed",
              "year": 2015,
              "sourceId": "inep_censo_escolar",
              "sourceField": "QT_MAT_INF_CRE"
            },
            "value2025": {
              "value": 860,
              "state": "observed",
              "year": 2025,
              "sourceId": "inep_censo_escolar",
              "sourceField": "QT_MAT_INF_CRE"
            },
            "absoluteChange": 337,
            "percentageChange": {
              "value": 64.43594646271511,
              "numerator": 337,
              "denominator": 523,
              "state": "observed",
              "year": 2025,
              "sourceId": "inep_censo_escolar"
            }
          },
          "state": {
            "value2015": {
              "value": 0,
              "state": "derived_zero",
              "year": 2015,
              "sourceId": "inep_censo_escolar",
              "sourceField": "QT_MAT_INF_CRE"
            },
            "value2025": {
              "value": 0,
              "state": "derived_zero",
              "year": 2025,
              "sourceId": "inep_censo_escolar",
              "sourceField": "QT_MAT_INF_CRE"
            },
            "absoluteChange": 0,
            "percentageChange": {
              "value": null,
              "numerator": 0,
              "denominator": 0,
              "state": "not_applicable",
              "year": 2025,
              "sourceId": "inep_censo_escolar"
            }
          },
          "federal": {
            "value2015": {
              "value": 0,
              "state": "derived_zero",
              "year": 2015,
              "sourceId": "inep_censo_escolar",
              "sourceField": "QT_MAT_INF_CRE"
            },
            "value2025": {
              "value": 0,
              "state": "derived_zero",
              "year": 2025,
              "sourceId": "inep_censo_escolar",
              "sourceField": "QT_MAT_INF_CRE"
            },
            "absoluteChange": 0,
            "percentageChange": {
              "value": null,
              "numerator": 0,
              "denominator": 0,
              "state": "not_applicable",
              "year": 2025,
              "sourceId": "inep_censo_escolar"
            }
          },
          "private": {
            "value2015": {
              "value": 232,
              "state": "observed",
              "year": 2015,
              "sourceId": "inep_censo_escolar",
              "sourceField": "QT_MAT_INF_CRE"
            },
            "value2025": {
              "value": 80,
              "state": "observed",
              "year": 2025,
              "sourceId": "inep_censo_escolar",
              "sourceField": "QT_MAT_INF_CRE"
            },
            "absoluteChange": -152,
            "percentageChange": {
              "value": -65.51724137931035,
              "numerator": -152,
              "denominator": 232,
              "state": "observed",
              "year": 2025,
              "sourceId": "inep_censo_escolar"
            }
          }
        },
        "bySchoolLocation": {
          "urban": {
            "value2015": {
              "value": 755,
              "state": "observed",
              "year": 2015,
              "sourceId": "inep_censo_escolar",
              "sourceField": "QT_MAT_INF_CRE"
            },
            "value2025": {
              "value": 940,
              "state": "observed",
              "year": 2025,
              "sourceId": "inep_censo_escolar",
              "sourceField": "QT_MAT_INF_CRE"
            },
            "absoluteChange": 185,
            "percentageChange": {
              "value": 24.503311258278146,
              "numerator": 185,
              "denominator": 755,
              "state": "observed",
              "year": 2025,
              "sourceId": "inep_censo_escolar"
            }
          },
          "rural": {
            "value2015": {
              "value": 0,
              "state": "derived_zero",
              "year": 2015,
              "sourceId": "inep_censo_escolar",
              "sourceField": "QT_MAT_INF_CRE"
            },
            "value2025": {
              "value": 0,
              "state": "derived_zero",
              "year": 2025,
              "sourceId": "inep_censo_escolar",
              "sourceField": "QT_MAT_INF_CRE"
            },
            "absoluteChange": 0,
            "percentageChange": {
              "value": null,
              "numerator": 0,
              "denominator": 0,
              "state": "not_applicable",
              "year": 2025,
              "sourceId": "inep_censo_escolar"
            }
          }
        }
      },
      "preSchool": {
        "total": {
          "value2015": {
            "value": 1245,
            "state": "observed",
            "year": 2015,
            "sourceId": "inep_censo_escolar",
            "sourceField": "QT_MAT_INF_PRE"
          },
          "value2025": {
            "value": 1340,
            "state": "observed",
            "year": 2025,
            "sourceId": "inep_censo_escolar",
            "sourceField": "QT_MAT_INF_PRE"
          },
          "absoluteChange": 95,
          "percentageChange": {
            "value": 7.630522088353414,
            "numerator": 95,
            "denominator": 1245,
            "state": "observed",
            "year": 2025,
            "sourceId": "inep_censo_escolar"
          }
        },
        "byNetwork": {
          "publicSubtotal": {
            "value2015": {
              "value": 1069,
              "state": "observed",
              "year": 2015,
              "sourceId": "inep_censo_escolar",
              "sourceField": "derived:municipal+estadual+federal"
            },
            "value2025": {
              "value": 1220,
              "state": "observed",
              "year": 2025,
              "sourceId": "inep_censo_escolar",
              "sourceField": "derived:municipal+estadual+federal"
            },
            "absoluteChange": 151,
            "percentageChange": {
              "value": 14.125350795135642,
              "numerator": 151,
              "denominator": 1069,
              "state": "observed",
              "year": 2025,
              "sourceId": "inep_censo_escolar"
            }
          },
          "municipal": {
            "value2015": {
              "value": 971,
              "state": "observed",
              "year": 2015,
              "sourceId": "inep_censo_escolar",
              "sourceField": "QT_MAT_INF_PRE"
            },
            "value2025": {
              "value": 1220,
              "state": "observed",
              "year": 2025,
              "sourceId": "inep_censo_escolar",
              "sourceField": "QT_MAT_INF_PRE"
            },
            "absoluteChange": 249,
            "percentageChange": {
              "value": 25.64366632337796,
              "numerator": 249,
              "denominator": 971,
              "state": "observed",
              "year": 2025,
              "sourceId": "inep_censo_escolar"
            }
          },
          "state": {
            "value2015": {
              "value": 98,
              "state": "observed",
              "year": 2015,
              "sourceId": "inep_censo_escolar",
              "sourceField": "QT_MAT_INF_PRE"
            },
            "value2025": {
              "value": 0,
              "state": "derived_zero",
              "year": 2025,
              "sourceId": "inep_censo_escolar",
              "sourceField": "QT_MAT_INF_PRE"
            },
            "absoluteChange": -98,
            "percentageChange": {
              "value": -100.0,
              "numerator": -98,
              "denominator": 98,
              "state": "observed",
              "year": 2025,
              "sourceId": "inep_censo_escolar"
            }
          },
          "federal": {
            "value2015": {
              "value": 0,
              "state": "derived_zero",
              "year": 2015,
              "sourceId": "inep_censo_escolar",
              "sourceField": "QT_MAT_INF_PRE"
            },
            "value2025": {
              "value": 0,
              "state": "derived_zero",
              "year": 2025,
              "sourceId": "inep_censo_escolar",
              "sourceField": "QT_MAT_INF_PRE"
            },
            "absoluteChange": 0,
            "percentageChange": {
              "value": null,
              "numerator": 0,
              "denominator": 0,
              "state": "not_applicable",
              "year": 2025,
              "sourceId": "inep_censo_escolar"
            }
          },
          "private": {
            "value2015": {
              "value": 176,
              "state": "observed",
              "year": 2015,
              "sourceId": "inep_censo_escolar",
              "sourceField": "QT_MAT_INF_PRE"
            },
            "value2025": {
              "value": 120,
              "state": "observed",
              "year": 2025,
              "sourceId": "inep_censo_escolar",
              "sourceField": "QT_MAT_INF_PRE"
            },
            "absoluteChange": -56,
            "percentageChange": {
              "value": -31.818181818181817,
              "numerator": -56,
              "denominator": 176,
              "state": "observed",
              "year": 2025,
              "sourceId": "inep_censo_escolar"
            }
          }
        },
        "bySchoolLocation": {
          "urban": {
            "value2015": {
              "value": 1164,
              "state": "observed",
              "year": 2015,
              "sourceId": "inep_censo_escolar",
              "sourceField": "QT_MAT_INF_PRE"
            },
            "value2025": {
              "value": 1230,
              "state": "observed",
              "year": 2025,
              "sourceId": "inep_censo_escolar",
              "sourceField": "QT_MAT_INF_PRE"
            },
            "absoluteChange": 66,
            "percentageChange": {
              "value": 5.670103092783505,
              "numerator": 66,
              "denominator": 1164,
              "state": "observed",
              "year": 2025,
              "sourceId": "inep_censo_escolar"
            }
          },
          "rural": {
            "value2015": {
              "value": 81,
              "state": "observed",
              "year": 2015,
              "sourceId": "inep_censo_escolar",
              "sourceField": "QT_MAT_INF_PRE"
            },
            "value2025": {
              "value": 110,
              "state": "observed",
              "year": 2025,
              "sourceId": "inep_censo_escolar",
              "sourceField": "QT_MAT_INF_PRE"
            },
            "absoluteChange": 29,
            "percentageChange": {
              "value": 35.80246913580247,
              "numerator": 29,
              "denominator": 81,
              "state": "observed",
              "year": 2025,
              "sourceId": "inep_censo_escolar"
            }
          }
        }
      },
      "elementary": {
        "total": {
          "value2015": {
            "value": 7702,
            "state": "observed",
            "year": 2015,
            "sourceId": "inep_censo_escolar",
            "sourceField": "QT_MAT_FUND"
          },
          "value2025": {
            "value": 6452,
            "state": "observed",
            "year": 2025,
            "sourceId": "inep_censo_escolar",
            "sourceField": "QT_MAT_FUND"
          },
          "absoluteChange": -1250,
          "percentageChange": {
            "value": -16.229550766034794,
            "numerator": -1250,
            "denominator": 7702,
            "state": "observed",
            "year": 2025,
            "sourceId": "inep_censo_escolar"
          }
        },
        "byNetwork": {
          "publicSubtotal": {
            "value2015": {
              "value": 7271,
              "state": "observed",
              "year": 2015,
              "sourceId": "inep_censo_escolar",
              "sourceField": "derived:municipal+estadual+federal"
            },
            "value2025": {
              "value": 5844,
              "state": "observed",
              "year": 2025,
              "sourceId": "inep_censo_escolar",
              "sourceField": "derived:municipal+estadual+federal"
            },
            "absoluteChange": -1427,
            "percentageChange": {
              "value": -19.62591115389905,
              "numerator": -1427,
              "denominator": 7271,
              "state": "observed",
              "year": 2025,
              "sourceId": "inep_censo_escolar"
            }
          },
          "municipal": {
            "value2015": {
              "value": 3267,
              "state": "observed",
              "year": 2015,
              "sourceId": "inep_censo_escolar",
              "sourceField": "QT_MAT_FUND"
            },
            "value2025": {
              "value": 2850,
              "state": "observed",
              "year": 2025,
              "sourceId": "inep_censo_escolar",
              "sourceField": "QT_MAT_FUND"
            },
            "absoluteChange": -417,
            "percentageChange": {
              "value": -12.764003673094582,
              "numerator": -417,
              "denominator": 3267,
              "state": "observed",
              "year": 2025,
              "sourceId": "inep_censo_escolar"
            }
          },
          "state": {
            "value2015": {
              "value": 4004,
              "state": "observed",
              "year": 2015,
              "sourceId": "inep_censo_escolar",
              "sourceField": "QT_MAT_FUND"
            },
            "value2025": {
              "value": 2994,
              "state": "observed",
              "year": 2025,
              "sourceId": "inep_censo_escolar",
              "sourceField": "QT_MAT_FUND"
            },
            "absoluteChange": -1010,
            "percentageChange": {
              "value": -25.224775224775225,
              "numerator": -1010,
              "denominator": 4004,
              "state": "observed",
              "year": 2025,
              "sourceId": "inep_censo_escolar"
            }
          },
          "federal": {
            "value2015": {
              "value": 0,
              "state": "derived_zero",
              "year": 2015,
              "sourceId": "inep_censo_escolar",
              "sourceField": "QT_MAT_FUND"
            },
            "value2025": {
              "value": 0,
              "state": "derived_zero",
              "year": 2025,
              "sourceId": "inep_censo_escolar",
              "sourceField": "QT_MAT_FUND"
            },
            "absoluteChange": 0,
            "percentageChange": {
              "value": null,
              "numerator": 0,
              "denominator": 0,
              "state": "not_applicable",
              "year": 2025,
              "sourceId": "inep_censo_escolar"
            }
          },
          "private": {
            "value2015": {
              "value": 431,
              "state": "observed",
              "year": 2015,
              "sourceId": "inep_censo_escolar",
              "sourceField": "QT_MAT_FUND"
            },
            "value2025": {
              "value": 608,
              "state": "observed",
              "year": 2025,
              "sourceId": "inep_censo_escolar",
              "sourceField": "QT_MAT_FUND"
            },
            "absoluteChange": 177,
            "percentageChange": {
              "value": 41.067285382830626,
              "numerator": 177,
              "denominator": 431,
              "state": "observed",
              "year": 2025,
              "sourceId": "inep_censo_escolar"
            }
          }
        },
        "bySchoolLocation": {
          "urban": {
            "value2015": {
              "value": 6895,
              "state": "observed",
              "year": 2015,
              "sourceId": "inep_censo_escolar",
              "sourceField": "QT_MAT_FUND"
            },
            "value2025": {
              "value": 5907,
              "state": "observed",
              "year": 2025,
              "sourceId": "inep_censo_escolar",
              "sourceField": "QT_MAT_FUND"
            },
            "absoluteChange": -988,
            "percentageChange": {
              "value": -14.329224075416969,
              "numerator": -988,
              "denominator": 6895,
              "state": "observed",
              "year": 2025,
              "sourceId": "inep_censo_escolar"
            }
          },
          "rural": {
            "value2015": {
              "value": 807,
              "state": "observed",
              "year": 2015,
              "sourceId": "inep_censo_escolar",
              "sourceField": "QT_MAT_FUND"
            },
            "value2025": {
              "value": 545,
              "state": "observed",
              "year": 2025,
              "sourceId": "inep_censo_escolar",
              "sourceField": "QT_MAT_FUND"
            },
            "absoluteChange": -262,
            "percentageChange": {
              "value": -32.465923172242874,
              "numerator": -262,
              "denominator": 807,
              "state": "observed",
              "year": 2025,
              "sourceId": "inep_censo_escolar"
            }
          }
        }
      },
      "initialYears": {
        "total": {
          "value2015": {
            "value": 4051,
            "state": "observed",
            "year": 2015,
            "sourceId": "inep_censo_escolar",
            "sourceField": "QT_MAT_FUND_AI"
          },
          "value2025": {
            "value": 3693,
            "state": "observed",
            "year": 2025,
            "sourceId": "inep_censo_escolar",
            "sourceField": "QT_MAT_FUND_AI"
          },
          "absoluteChange": -358,
          "percentageChange": {
            "value": -8.837324117501852,
            "numerator": -358,
            "denominator": 4051,
            "state": "observed",
            "year": 2025,
            "sourceId": "inep_censo_escolar"
          }
        },
        "byNetwork": {
          "publicSubtotal": {
            "value2015": {
              "value": 3766,
              "state": "observed",
              "year": 2015,
              "sourceId": "inep_censo_escolar",
              "sourceField": "derived:municipal+estadual+federal"
            },
            "value2025": {
              "value": 3337,
              "state": "observed",
              "year": 2025,
              "sourceId": "inep_censo_escolar",
              "sourceField": "derived:municipal+estadual+federal"
            },
            "absoluteChange": -429,
            "percentageChange": {
              "value": -11.391396707381837,
              "numerator": -429,
              "denominator": 3766,
              "state": "observed",
              "year": 2025,
              "sourceId": "inep_censo_escolar"
            }
          },
          "municipal": {
            "value2015": {
              "value": 2128,
              "state": "observed",
              "year": 2015,
              "sourceId": "inep_censo_escolar",
              "sourceField": "QT_MAT_FUND_AI"
            },
            "value2025": {
              "value": 2026,
              "state": "observed",
              "year": 2025,
              "sourceId": "inep_censo_escolar",
              "sourceField": "QT_MAT_FUND_AI"
            },
            "absoluteChange": -102,
            "percentageChange": {
              "value": -4.793233082706767,
              "numerator": -102,
              "denominator": 2128,
              "state": "observed",
              "year": 2025,
              "sourceId": "inep_censo_escolar"
            }
          },
          "state": {
            "value2015": {
              "value": 1638,
              "state": "observed",
              "year": 2015,
              "sourceId": "inep_censo_escolar",
              "sourceField": "QT_MAT_FUND_AI"
            },
            "value2025": {
              "value": 1311,
              "state": "observed",
              "year": 2025,
              "sourceId": "inep_censo_escolar",
              "sourceField": "QT_MAT_FUND_AI"
            },
            "absoluteChange": -327,
            "percentageChange": {
              "value": -19.963369963369964,
              "numerator": -327,
              "denominator": 1638,
              "state": "observed",
              "year": 2025,
              "sourceId": "inep_censo_escolar"
            }
          },
          "federal": {
            "value2015": {
              "value": 0,
              "state": "derived_zero",
              "year": 2015,
              "sourceId": "inep_censo_escolar",
              "sourceField": "QT_MAT_FUND_AI"
            },
            "value2025": {
              "value": 0,
              "state": "derived_zero",
              "year": 2025,
              "sourceId": "inep_censo_escolar",
              "sourceField": "QT_MAT_FUND_AI"
            },
            "absoluteChange": 0,
            "percentageChange": {
              "value": null,
              "numerator": 0,
              "denominator": 0,
              "state": "not_applicable",
              "year": 2025,
              "sourceId": "inep_censo_escolar"
            }
          },
          "private": {
            "value2015": {
              "value": 285,
              "state": "observed",
              "year": 2015,
              "sourceId": "inep_censo_escolar",
              "sourceField": "QT_MAT_FUND_AI"
            },
            "value2025": {
              "value": 356,
              "state": "observed",
              "year": 2025,
              "sourceId": "inep_censo_escolar",
              "sourceField": "QT_MAT_FUND_AI"
            },
            "absoluteChange": 71,
            "percentageChange": {
              "value": 24.912280701754387,
              "numerator": 71,
              "denominator": 285,
              "state": "observed",
              "year": 2025,
              "sourceId": "inep_censo_escolar"
            }
          }
        },
        "bySchoolLocation": {
          "urban": {
            "value2015": {
              "value": 3613,
              "state": "observed",
              "year": 2015,
              "sourceId": "inep_censo_escolar",
              "sourceField": "QT_MAT_FUND_AI"
            },
            "value2025": {
              "value": 3371,
              "state": "observed",
              "year": 2025,
              "sourceId": "inep_censo_escolar",
              "sourceField": "QT_MAT_FUND_AI"
            },
            "absoluteChange": -242,
            "percentageChange": {
              "value": -6.698034874065874,
              "numerator": -242,
              "denominator": 3613,
              "state": "observed",
              "year": 2025,
              "sourceId": "inep_censo_escolar"
            }
          },
          "rural": {
            "value2015": {
              "value": 438,
              "state": "observed",
              "year": 2015,
              "sourceId": "inep_censo_escolar",
              "sourceField": "QT_MAT_FUND_AI"
            },
            "value2025": {
              "value": 322,
              "state": "observed",
              "year": 2025,
              "sourceId": "inep_censo_escolar",
              "sourceField": "QT_MAT_FUND_AI"
            },
            "absoluteChange": -116,
            "percentageChange": {
              "value": -26.48401826484018,
              "numerator": -116,
              "denominator": 438,
              "state": "observed",
              "year": 2025,
              "sourceId": "inep_censo_escolar"
            }
          }
        }
      },
      "finalYears": {
        "total": {
          "value2015": {
            "value": 3651,
            "state": "observed",
            "year": 2015,
            "sourceId": "inep_censo_escolar",
            "sourceField": "QT_MAT_FUND_AF"
          },
          "value2025": {
            "value": 2759,
            "state": "observed",
            "year": 2025,
            "sourceId": "inep_censo_escolar",
            "sourceField": "QT_MAT_FUND_AF"
          },
          "absoluteChange": -892,
          "percentageChange": {
            "value": -24.431662558203232,
            "numerator": -892,
            "denominator": 3651,
            "state": "observed",
            "year": 2025,
            "sourceId": "inep_censo_escolar"
          }
        },
        "byNetwork": {
          "publicSubtotal": {
            "value2015": {
              "value": 3505,
              "state": "observed",
              "year": 2015,
              "sourceId": "inep_censo_escolar",
              "sourceField": "derived:municipal+estadual+federal"
            },
            "value2025": {
              "value": 2507,
              "state": "observed",
              "year": 2025,
              "sourceId": "inep_censo_escolar",
              "sourceField": "derived:municipal+estadual+federal"
            },
            "absoluteChange": -998,
            "percentageChange": {
              "value": -28.47360912981455,
              "numerator": -998,
              "denominator": 3505,
              "state": "observed",
              "year": 2025,
              "sourceId": "inep_censo_escolar"
            }
          },
          "municipal": {
            "value2015": {
              "value": 1139,
              "state": "observed",
              "year": 2015,
              "sourceId": "inep_censo_escolar",
              "sourceField": "QT_MAT_FUND_AF"
            },
            "value2025": {
              "value": 824,
              "state": "observed",
              "year": 2025,
              "sourceId": "inep_censo_escolar",
              "sourceField": "QT_MAT_FUND_AF"
            },
            "absoluteChange": -315,
            "percentageChange": {
              "value": -27.6558384547849,
              "numerator": -315,
              "denominator": 1139,
              "state": "observed",
              "year": 2025,
              "sourceId": "inep_censo_escolar"
            }
          },
          "state": {
            "value2015": {
              "value": 2366,
              "state": "observed",
              "year": 2015,
              "sourceId": "inep_censo_escolar",
              "sourceField": "QT_MAT_FUND_AF"
            },
            "value2025": {
              "value": 1683,
              "state": "observed",
              "year": 2025,
              "sourceId": "inep_censo_escolar",
              "sourceField": "QT_MAT_FUND_AF"
            },
            "absoluteChange": -683,
            "percentageChange": {
              "value": -28.867286559594252,
              "numerator": -683,
              "denominator": 2366,
              "state": "observed",
              "year": 2025,
              "sourceId": "inep_censo_escolar"
            }
          },
          "federal": {
            "value2015": {
              "value": 0,
              "state": "derived_zero",
              "year": 2015,
              "sourceId": "inep_censo_escolar",
              "sourceField": "QT_MAT_FUND_AF"
            },
            "value2025": {
              "value": 0,
              "state": "derived_zero",
              "year": 2025,
              "sourceId": "inep_censo_escolar",
              "sourceField": "QT_MAT_FUND_AF"
            },
            "absoluteChange": 0,
            "percentageChange": {
              "value": null,
              "numerator": 0,
              "denominator": 0,
              "state": "not_applicable",
              "year": 2025,
              "sourceId": "inep_censo_escolar"
            }
          },
          "private": {
            "value2015": {
              "value": 146,
              "state": "observed",
              "year": 2015,
              "sourceId": "inep_censo_escolar",
              "sourceField": "QT_MAT_FUND_AF"
            },
            "value2025": {
              "value": 252,
              "state": "observed",
              "year": 2025,
              "sourceId": "inep_censo_escolar",
              "sourceField": "QT_MAT_FUND_AF"
            },
            "absoluteChange": 106,
            "percentageChange": {
              "value": 72.6027397260274,
              "numerator": 106,
              "denominator": 146,
              "state": "observed",
              "year": 2025,
              "sourceId": "inep_censo_escolar"
            }
          }
        },
        "bySchoolLocation": {
          "urban": {
            "value2015": {
              "value": 3282,
              "state": "observed",
              "year": 2015,
              "sourceId": "inep_censo_escolar",
              "sourceField": "QT_MAT_FUND_AF"
            },
            "value2025": {
              "value": 2536,
              "state": "observed",
              "year": 2025,
              "sourceId": "inep_censo_escolar",
              "sourceField": "QT_MAT_FUND_AF"
            },
            "absoluteChange": -746,
            "percentageChange": {
              "value": -22.730042656916513,
              "numerator": -746,
              "denominator": 3282,
              "state": "observed",
              "year": 2025,
              "sourceId": "inep_censo_escolar"
            }
          },
          "rural": {
            "value2015": {
              "value": 369,
              "state": "observed",
              "year": 2015,
              "sourceId": "inep_censo_escolar",
              "sourceField": "QT_MAT_FUND_AF"
            },
            "value2025": {
              "value": 223,
              "state": "observed",
              "year": 2025,
              "sourceId": "inep_censo_escolar",
              "sourceField": "QT_MAT_FUND_AF"
            },
            "absoluteChange": -146,
            "percentageChange": {
              "value": -39.56639566395664,
              "numerator": -146,
              "denominator": 369,
              "state": "observed",
              "year": 2025,
              "sourceId": "inep_censo_escolar"
            }
          }
        }
      },
      "highSchool": {
        "total": {
          "value2015": {
            "value": 2391,
            "state": "observed",
            "year": 2015,
            "sourceId": "inep_censo_escolar",
            "sourceField": "QT_MAT_MED"
          },
          "value2025": {
            "value": 1746,
            "state": "observed",
            "year": 2025,
            "sourceId": "inep_censo_escolar",
            "sourceField": "QT_MAT_MED"
          },
          "absoluteChange": -645,
          "percentageChange": {
            "value": -26.97616060225847,
            "numerator": -645,
            "denominator": 2391,
            "state": "observed",
            "year": 2025,
            "sourceId": "inep_censo_escolar"
          }
        },
        "byNetwork": {
          "publicSubtotal": {
            "value2015": {
              "value": 2287,
              "state": "observed",
              "year": 2015,
              "sourceId": "inep_censo_escolar",
              "sourceField": "derived:municipal+estadual+federal"
            },
            "value2025": {
              "value": 1665,
              "state": "observed",
              "year": 2025,
              "sourceId": "inep_censo_escolar",
              "sourceField": "derived:municipal+estadual+federal"
            },
            "absoluteChange": -622,
            "percentageChange": {
              "value": -27.19720157411456,
              "numerator": -622,
              "denominator": 2287,
              "state": "observed",
              "year": 2025,
              "sourceId": "inep_censo_escolar"
            }
          },
          "municipal": {
            "value2015": {
              "value": 0,
              "state": "derived_zero",
              "year": 2015,
              "sourceId": "inep_censo_escolar",
              "sourceField": "QT_MAT_MED"
            },
            "value2025": {
              "value": 0,
              "state": "derived_zero",
              "year": 2025,
              "sourceId": "inep_censo_escolar",
              "sourceField": "QT_MAT_MED"
            },
            "absoluteChange": 0,
            "percentageChange": {
              "value": null,
              "numerator": 0,
              "denominator": 0,
              "state": "not_applicable",
              "year": 2025,
              "sourceId": "inep_censo_escolar"
            }
          },
          "state": {
            "value2015": {
              "value": 1967,
              "state": "observed",
              "year": 2015,
              "sourceId": "inep_censo_escolar",
              "sourceField": "QT_MAT_MED"
            },
            "value2025": {
              "value": 1275,
              "state": "observed",
              "year": 2025,
              "sourceId": "inep_censo_escolar",
              "sourceField": "QT_MAT_MED"
            },
            "absoluteChange": -692,
            "percentageChange": {
              "value": -35.180477885104224,
              "numerator": -692,
              "denominator": 1967,
              "state": "observed",
              "year": 2025,
              "sourceId": "inep_censo_escolar"
            }
          },
          "federal": {
            "value2015": {
              "value": 320,
              "state": "observed",
              "year": 2015,
              "sourceId": "inep_censo_escolar",
              "sourceField": "QT_MAT_MED"
            },
            "value2025": {
              "value": 390,
              "state": "observed",
              "year": 2025,
              "sourceId": "inep_censo_escolar",
              "sourceField": "QT_MAT_MED"
            },
            "absoluteChange": 70,
            "percentageChange": {
              "value": 21.875,
              "numerator": 70,
              "denominator": 320,
              "state": "observed",
              "year": 2025,
              "sourceId": "inep_censo_escolar"
            }
          },
          "private": {
            "value2015": {
              "value": 104,
              "state": "observed",
              "year": 2015,
              "sourceId": "inep_censo_escolar",
              "sourceField": "QT_MAT_MED"
            },
            "value2025": {
              "value": 81,
              "state": "observed",
              "year": 2025,
              "sourceId": "inep_censo_escolar",
              "sourceField": "QT_MAT_MED"
            },
            "absoluteChange": -23,
            "percentageChange": {
              "value": -22.115384615384613,
              "numerator": -23,
              "denominator": 104,
              "state": "observed",
              "year": 2025,
              "sourceId": "inep_censo_escolar"
            }
          }
        },
        "bySchoolLocation": {
          "urban": {
            "value2015": {
              "value": 2235,
              "state": "observed",
              "year": 2015,
              "sourceId": "inep_censo_escolar",
              "sourceField": "QT_MAT_MED"
            },
            "value2025": {
              "value": 1685,
              "state": "observed",
              "year": 2025,
              "sourceId": "inep_censo_escolar",
              "sourceField": "QT_MAT_MED"
            },
            "absoluteChange": -550,
            "percentageChange": {
              "value": -24.60850111856823,
              "numerator": -550,
              "denominator": 2235,
              "state": "observed",
              "year": 2025,
              "sourceId": "inep_censo_escolar"
            }
          },
          "rural": {
            "value2015": {
              "value": 156,
              "state": "observed",
              "year": 2015,
              "sourceId": "inep_censo_escolar",
              "sourceField": "QT_MAT_MED"
            },
            "value2025": {
              "value": 61,
              "state": "observed",
              "year": 2025,
              "sourceId": "inep_censo_escolar",
              "sourceField": "QT_MAT_MED"
            },
            "absoluteChange": -95,
            "percentageChange": {
              "value": -60.89743589743589,
              "numerator": -95,
              "denominator": 156,
              "state": "observed",
              "year": 2025,
              "sourceId": "inep_censo_escolar"
            }
          }
        }
      },
      "youthAndAdultEducation": {
        "total": {
          "value2015": {
            "value": 1600,
            "state": "observed",
            "year": 2015,
            "sourceId": "inep_censo_escolar",
            "sourceField": "QT_MAT_EJA"
          },
          "value2025": {
            "value": 390,
            "state": "observed",
            "year": 2025,
            "sourceId": "inep_censo_escolar",
            "sourceField": "QT_MAT_EJA"
          },
          "absoluteChange": -1210,
          "percentageChange": {
            "value": -75.625,
            "numerator": -1210,
            "denominator": 1600,
            "state": "observed",
            "year": 2025,
            "sourceId": "inep_censo_escolar"
          }
        },
        "byNetwork": {
          "publicSubtotal": {
            "value2015": {
              "value": 1529,
              "state": "observed",
              "year": 2015,
              "sourceId": "inep_censo_escolar",
              "sourceField": "derived:municipal+estadual+federal"
            },
            "value2025": {
              "value": 360,
              "state": "observed",
              "year": 2025,
              "sourceId": "inep_censo_escolar",
              "sourceField": "derived:municipal+estadual+federal"
            },
            "absoluteChange": -1169,
            "percentageChange": {
              "value": -76.45519947678221,
              "numerator": -1169,
              "denominator": 1529,
              "state": "observed",
              "year": 2025,
              "sourceId": "inep_censo_escolar"
            }
          },
          "municipal": {
            "value2015": {
              "value": 57,
              "state": "observed",
              "year": 2015,
              "sourceId": "inep_censo_escolar",
              "sourceField": "QT_MAT_EJA"
            },
            "value2025": {
              "value": 0,
              "state": "derived_zero",
              "year": 2025,
              "sourceId": "inep_censo_escolar",
              "sourceField": "QT_MAT_EJA"
            },
            "absoluteChange": -57,
            "percentageChange": {
              "value": -100.0,
              "numerator": -57,
              "denominator": 57,
              "state": "observed",
              "year": 2025,
              "sourceId": "inep_censo_escolar"
            }
          },
          "state": {
            "value2015": {
              "value": 1431,
              "state": "observed",
              "year": 2015,
              "sourceId": "inep_censo_escolar",
              "sourceField": "QT_MAT_EJA"
            },
            "value2025": {
              "value": 355,
              "state": "observed",
              "year": 2025,
              "sourceId": "inep_censo_escolar",
              "sourceField": "QT_MAT_EJA"
            },
            "absoluteChange": -1076,
            "percentageChange": {
              "value": -75.19217330538085,
              "numerator": -1076,
              "denominator": 1431,
              "state": "observed",
              "year": 2025,
              "sourceId": "inep_censo_escolar"
            }
          },
          "federal": {
            "value2015": {
              "value": 41,
              "state": "observed",
              "year": 2015,
              "sourceId": "inep_censo_escolar",
              "sourceField": "QT_MAT_EJA"
            },
            "value2025": {
              "value": 5,
              "state": "observed",
              "year": 2025,
              "sourceId": "inep_censo_escolar",
              "sourceField": "QT_MAT_EJA"
            },
            "absoluteChange": -36,
            "percentageChange": {
              "value": -87.8048780487805,
              "numerator": -36,
              "denominator": 41,
              "state": "observed",
              "year": 2025,
              "sourceId": "inep_censo_escolar"
            }
          },
          "private": {
            "value2015": {
              "value": 71,
              "state": "observed",
              "year": 2015,
              "sourceId": "inep_censo_escolar",
              "sourceField": "QT_MAT_EJA"
            },
            "value2025": {
              "value": 30,
              "state": "observed",
              "year": 2025,
              "sourceId": "inep_censo_escolar",
              "sourceField": "QT_MAT_EJA"
            },
            "absoluteChange": -41,
            "percentageChange": {
              "value": -57.74647887323944,
              "numerator": -41,
              "denominator": 71,
              "state": "observed",
              "year": 2025,
              "sourceId": "inep_censo_escolar"
            }
          }
        },
        "bySchoolLocation": {
          "urban": {
            "value2015": {
              "value": 1600,
              "state": "observed",
              "year": 2015,
              "sourceId": "inep_censo_escolar",
              "sourceField": "QT_MAT_EJA"
            },
            "value2025": {
              "value": 390,
              "state": "observed",
              "year": 2025,
              "sourceId": "inep_censo_escolar",
              "sourceField": "QT_MAT_EJA"
            },
            "absoluteChange": -1210,
            "percentageChange": {
              "value": -75.625,
              "numerator": -1210,
              "denominator": 1600,
              "state": "observed",
              "year": 2025,
              "sourceId": "inep_censo_escolar"
            }
          },
          "rural": {
            "value2015": {
              "value": 0,
              "state": "derived_zero",
              "year": 2015,
              "sourceId": "inep_censo_escolar",
              "sourceField": "QT_MAT_EJA"
            },
            "value2025": {
              "value": 0,
              "state": "derived_zero",
              "year": 2025,
              "sourceId": "inep_censo_escolar",
              "sourceField": "QT_MAT_EJA"
            },
            "absoluteChange": 0,
            "percentageChange": {
              "value": null,
              "numerator": 0,
              "denominator": 0,
              "state": "not_applicable",
              "year": 2025,
              "sourceId": "inep_censo_escolar"
            }
          }
        }
      }
    },
    "methodologyNote": "A variação é (matrículas de 2025 − matrículas de 2015) / matrículas de 2015 × 100. Base zero em 2015 e valores indisponíveis não produzem taxa."
  },
  "earlyChildhood": {
    "total": {
      "total": {
        "value": 2280,
        "state": "observed",
        "year": 2025,
        "sourceId": "inep_censo_escolar",
        "sourceField": "QT_MAT_INF"
      },
      "shareOfBasicEducation": {
        "value": 20.575760310441296,
        "numerator": 2280,
        "denominator": 11081,
        "state": "observed",
        "year": 2025,
        "sourceId": "inep_censo_escolar"
      },
      "byNetwork": {
        "publicSubtotal": {
          "enrollments": {
            "value": 2080,
            "state": "observed",
            "year": 2025,
            "sourceId": "inep_censo_escolar",
            "sourceField": "derived:municipal+estadual+federal"
          },
          "share": {
            "value": 91.22807017543859,
            "numerator": 2080,
            "denominator": 2280,
            "state": "observed",
            "year": 2025,
            "sourceId": "inep_censo_escolar"
          }
        },
        "municipal": {
          "enrollments": {
            "value": 2080,
            "state": "observed",
            "year": 2025,
            "sourceId": "inep_censo_escolar",
            "sourceField": "QT_MAT_INF"
          },
          "share": {
            "value": 91.22807017543859,
            "numerator": 2080,
            "denominator": 2280,
            "state": "observed",
            "year": 2025,
            "sourceId": "inep_censo_escolar"
          }
        },
        "state": {
          "enrollments": {
            "value": 0,
            "state": "derived_zero",
            "year": 2025,
            "sourceId": "inep_censo_escolar",
            "sourceField": "QT_MAT_INF"
          },
          "share": {
            "value": 0.0,
            "numerator": 0,
            "denominator": 2280,
            "state": "derived_zero",
            "year": 2025,
            "sourceId": "inep_censo_escolar"
          }
        },
        "federal": {
          "enrollments": {
            "value": 0,
            "state": "derived_zero",
            "year": 2025,
            "sourceId": "inep_censo_escolar",
            "sourceField": "QT_MAT_INF"
          },
          "share": {
            "value": 0.0,
            "numerator": 0,
            "denominator": 2280,
            "state": "derived_zero",
            "year": 2025,
            "sourceId": "inep_censo_escolar"
          }
        },
        "private": {
          "enrollments": {
            "value": 200,
            "state": "observed",
            "year": 2025,
            "sourceId": "inep_censo_escolar",
            "sourceField": "QT_MAT_INF"
          },
          "share": {
            "value": 8.771929824561402,
            "numerator": 200,
            "denominator": 2280,
            "state": "observed",
            "year": 2025,
            "sourceId": "inep_censo_escolar"
          }
        }
      },
      "bySchoolLocation": {
        "urban": {
          "enrollments": {
            "value": 2170,
            "state": "observed",
            "year": 2025,
            "sourceId": "inep_censo_escolar",
            "sourceField": "QT_MAT_INF"
          },
          "share": {
            "value": 95.17543859649122,
            "numerator": 2170,
            "denominator": 2280,
            "state": "observed",
            "year": 2025,
            "sourceId": "inep_censo_escolar"
          }
        },
        "rural": {
          "enrollments": {
            "value": 110,
            "state": "observed",
            "year": 2025,
            "sourceId": "inep_censo_escolar",
            "sourceField": "QT_MAT_INF"
          },
          "share": {
            "value": 4.824561403508771,
            "numerator": 110,
            "denominator": 2280,
            "state": "observed",
            "year": 2025,
            "sourceId": "inep_censo_escolar"
          }
        }
      }
    },
    "creche": {
      "total": {
        "value": 940,
        "state": "observed",
        "year": 2025,
        "sourceId": "inep_censo_escolar",
        "sourceField": "QT_MAT_INF_CRE"
      },
      "shareOfBasicEducation": {
        "value": 8.48298889991878,
        "numerator": 940,
        "denominator": 11081,
        "state": "observed",
        "year": 2025,
        "sourceId": "inep_censo_escolar"
      },
      "byNetwork": {
        "publicSubtotal": {
          "enrollments": {
            "value": 860,
            "state": "observed",
            "year": 2025,
            "sourceId": "inep_censo_escolar",
            "sourceField": "derived:municipal+estadual+federal"
          },
          "share": {
            "value": 91.48936170212765,
            "numerator": 860,
            "denominator": 940,
            "state": "observed",
            "year": 2025,
            "sourceId": "inep_censo_escolar"
          }
        },
        "municipal": {
          "enrollments": {
            "value": 860,
            "state": "observed",
            "year": 2025,
            "sourceId": "inep_censo_escolar",
            "sourceField": "QT_MAT_INF_CRE"
          },
          "share": {
            "value": 91.48936170212765,
            "numerator": 860,
            "denominator": 940,
            "state": "observed",
            "year": 2025,
            "sourceId": "inep_censo_escolar"
          }
        },
        "state": {
          "enrollments": {
            "value": 0,
            "state": "derived_zero",
            "year": 2025,
            "sourceId": "inep_censo_escolar",
            "sourceField": "QT_MAT_INF_CRE"
          },
          "share": {
            "value": 0.0,
            "numerator": 0,
            "denominator": 940,
            "state": "derived_zero",
            "year": 2025,
            "sourceId": "inep_censo_escolar"
          }
        },
        "federal": {
          "enrollments": {
            "value": 0,
            "state": "derived_zero",
            "year": 2025,
            "sourceId": "inep_censo_escolar",
            "sourceField": "QT_MAT_INF_CRE"
          },
          "share": {
            "value": 0.0,
            "numerator": 0,
            "denominator": 940,
            "state": "derived_zero",
            "year": 2025,
            "sourceId": "inep_censo_escolar"
          }
        },
        "private": {
          "enrollments": {
            "value": 80,
            "state": "observed",
            "year": 2025,
            "sourceId": "inep_censo_escolar",
            "sourceField": "QT_MAT_INF_CRE"
          },
          "share": {
            "value": 8.51063829787234,
            "numerator": 80,
            "denominator": 940,
            "state": "observed",
            "year": 2025,
            "sourceId": "inep_censo_escolar"
          }
        }
      },
      "bySchoolLocation": {
        "urban": {
          "enrollments": {
            "value": 940,
            "state": "observed",
            "year": 2025,
            "sourceId": "inep_censo_escolar",
            "sourceField": "QT_MAT_INF_CRE"
          },
          "share": {
            "value": 100.0,
            "numerator": 940,
            "denominator": 940,
            "state": "observed",
            "year": 2025,
            "sourceId": "inep_censo_escolar"
          }
        },
        "rural": {
          "enrollments": {
            "value": 0,
            "state": "derived_zero",
            "year": 2025,
            "sourceId": "inep_censo_escolar",
            "sourceField": "QT_MAT_INF_CRE"
          },
          "share": {
            "value": 0.0,
            "numerator": 0,
            "denominator": 940,
            "state": "derived_zero",
            "year": 2025,
            "sourceId": "inep_censo_escolar"
          }
        }
      },
      "shareOfParentStage": {
        "value": 41.228070175438596,
        "numerator": 940,
        "denominator": 2280,
        "state": "observed",
        "year": 2025,
        "sourceId": "inep_censo_escolar"
      }
    },
    "preSchool": {
      "total": {
        "value": 1340,
        "state": "observed",
        "year": 2025,
        "sourceId": "inep_censo_escolar",
        "sourceField": "QT_MAT_INF_PRE"
      },
      "shareOfBasicEducation": {
        "value": 12.092771410522515,
        "numerator": 1340,
        "denominator": 11081,
        "state": "observed",
        "year": 2025,
        "sourceId": "inep_censo_escolar"
      },
      "byNetwork": {
        "publicSubtotal": {
          "enrollments": {
            "value": 1220,
            "state": "observed",
            "year": 2025,
            "sourceId": "inep_censo_escolar",
            "sourceField": "derived:municipal+estadual+federal"
          },
          "share": {
            "value": 91.04477611940298,
            "numerator": 1220,
            "denominator": 1340,
            "state": "observed",
            "year": 2025,
            "sourceId": "inep_censo_escolar"
          }
        },
        "municipal": {
          "enrollments": {
            "value": 1220,
            "state": "observed",
            "year": 2025,
            "sourceId": "inep_censo_escolar",
            "sourceField": "QT_MAT_INF_PRE"
          },
          "share": {
            "value": 91.04477611940298,
            "numerator": 1220,
            "denominator": 1340,
            "state": "observed",
            "year": 2025,
            "sourceId": "inep_censo_escolar"
          }
        },
        "state": {
          "enrollments": {
            "value": 0,
            "state": "derived_zero",
            "year": 2025,
            "sourceId": "inep_censo_escolar",
            "sourceField": "QT_MAT_INF_PRE"
          },
          "share": {
            "value": 0.0,
            "numerator": 0,
            "denominator": 1340,
            "state": "derived_zero",
            "year": 2025,
            "sourceId": "inep_censo_escolar"
          }
        },
        "federal": {
          "enrollments": {
            "value": 0,
            "state": "derived_zero",
            "year": 2025,
            "sourceId": "inep_censo_escolar",
            "sourceField": "QT_MAT_INF_PRE"
          },
          "share": {
            "value": 0.0,
            "numerator": 0,
            "denominator": 1340,
            "state": "derived_zero",
            "year": 2025,
            "sourceId": "inep_censo_escolar"
          }
        },
        "private": {
          "enrollments": {
            "value": 120,
            "state": "observed",
            "year": 2025,
            "sourceId": "inep_censo_escolar",
            "sourceField": "QT_MAT_INF_PRE"
          },
          "share": {
            "value": 8.955223880597014,
            "numerator": 120,
            "denominator": 1340,
            "state": "observed",
            "year": 2025,
            "sourceId": "inep_censo_escolar"
          }
        }
      },
      "bySchoolLocation": {
        "urban": {
          "enrollments": {
            "value": 1230,
            "state": "observed",
            "year": 2025,
            "sourceId": "inep_censo_escolar",
            "sourceField": "QT_MAT_INF_PRE"
          },
          "share": {
            "value": 91.7910447761194,
            "numerator": 1230,
            "denominator": 1340,
            "state": "observed",
            "year": 2025,
            "sourceId": "inep_censo_escolar"
          }
        },
        "rural": {
          "enrollments": {
            "value": 110,
            "state": "observed",
            "year": 2025,
            "sourceId": "inep_censo_escolar",
            "sourceField": "QT_MAT_INF_PRE"
          },
          "share": {
            "value": 8.208955223880597,
            "numerator": 110,
            "denominator": 1340,
            "state": "observed",
            "year": 2025,
            "sourceId": "inep_censo_escolar"
          }
        }
      },
      "shareOfParentStage": {
        "value": 58.77192982456141,
        "numerator": 1340,
        "denominator": 2280,
        "state": "observed",
        "year": 2025,
        "sourceId": "inep_censo_escolar"
      }
    }
  },
  "elementary": {
    "total": {
      "total": {
        "value": 6452,
        "state": "observed",
        "year": 2025,
        "sourceId": "inep_censo_escolar",
        "sourceField": "QT_MAT_FUND"
      },
      "shareOfBasicEducation": {
        "value": 58.22579189603826,
        "numerator": 6452,
        "denominator": 11081,
        "state": "observed",
        "year": 2025,
        "sourceId": "inep_censo_escolar"
      },
      "byNetwork": {
        "publicSubtotal": {
          "enrollments": {
            "value": 5844,
            "state": "observed",
            "year": 2025,
            "sourceId": "inep_censo_escolar",
            "sourceField": "derived:municipal+estadual+federal"
          },
          "share": {
            "value": 90.57656540607564,
            "numerator": 5844,
            "denominator": 6452,
            "state": "observed",
            "year": 2025,
            "sourceId": "inep_censo_escolar"
          }
        },
        "municipal": {
          "enrollments": {
            "value": 2850,
            "state": "observed",
            "year": 2025,
            "sourceId": "inep_censo_escolar",
            "sourceField": "QT_MAT_FUND"
          },
          "share": {
            "value": 44.17234965902046,
            "numerator": 2850,
            "denominator": 6452,
            "state": "observed",
            "year": 2025,
            "sourceId": "inep_censo_escolar"
          }
        },
        "state": {
          "enrollments": {
            "value": 2994,
            "state": "observed",
            "year": 2025,
            "sourceId": "inep_censo_escolar",
            "sourceField": "QT_MAT_FUND"
          },
          "share": {
            "value": 46.404215747055176,
            "numerator": 2994,
            "denominator": 6452,
            "state": "observed",
            "year": 2025,
            "sourceId": "inep_censo_escolar"
          }
        },
        "federal": {
          "enrollments": {
            "value": 0,
            "state": "derived_zero",
            "year": 2025,
            "sourceId": "inep_censo_escolar",
            "sourceField": "QT_MAT_FUND"
          },
          "share": {
            "value": 0.0,
            "numerator": 0,
            "denominator": 6452,
            "state": "derived_zero",
            "year": 2025,
            "sourceId": "inep_censo_escolar"
          }
        },
        "private": {
          "enrollments": {
            "value": 608,
            "state": "observed",
            "year": 2025,
            "sourceId": "inep_censo_escolar",
            "sourceField": "QT_MAT_FUND"
          },
          "share": {
            "value": 9.423434593924366,
            "numerator": 608,
            "denominator": 6452,
            "state": "observed",
            "year": 2025,
            "sourceId": "inep_censo_escolar"
          }
        }
      },
      "bySchoolLocation": {
        "urban": {
          "enrollments": {
            "value": 5907,
            "state": "observed",
            "year": 2025,
            "sourceId": "inep_censo_escolar",
            "sourceField": "QT_MAT_FUND"
          },
          "share": {
            "value": 91.55300681959082,
            "numerator": 5907,
            "denominator": 6452,
            "state": "observed",
            "year": 2025,
            "sourceId": "inep_censo_escolar"
          }
        },
        "rural": {
          "enrollments": {
            "value": 545,
            "state": "observed",
            "year": 2025,
            "sourceId": "inep_censo_escolar",
            "sourceField": "QT_MAT_FUND"
          },
          "share": {
            "value": 8.446993180409175,
            "numerator": 545,
            "denominator": 6452,
            "state": "observed",
            "year": 2025,
            "sourceId": "inep_censo_escolar"
          }
        }
      }
    },
    "initialYears": {
      "total": {
        "value": 3693,
        "state": "observed",
        "year": 2025,
        "sourceId": "inep_censo_escolar",
        "sourceField": "QT_MAT_FUND_AI"
      },
      "shareOfBasicEducation": {
        "value": 33.32731702914899,
        "numerator": 3693,
        "denominator": 11081,
        "state": "observed",
        "year": 2025,
        "sourceId": "inep_censo_escolar"
      },
      "byNetwork": {
        "publicSubtotal": {
          "enrollments": {
            "value": 3337,
            "state": "observed",
            "year": 2025,
            "sourceId": "inep_censo_escolar",
            "sourceField": "derived:municipal+estadual+federal"
          },
          "share": {
            "value": 90.36014080693204,
            "numerator": 3337,
            "denominator": 3693,
            "state": "observed",
            "year": 2025,
            "sourceId": "inep_censo_escolar"
          }
        },
        "municipal": {
          "enrollments": {
            "value": 2026,
            "state": "observed",
            "year": 2025,
            "sourceId": "inep_censo_escolar",
            "sourceField": "QT_MAT_FUND_AI"
          },
          "share": {
            "value": 54.86054698077444,
            "numerator": 2026,
            "denominator": 3693,
            "state": "observed",
            "year": 2025,
            "sourceId": "inep_censo_escolar"
          }
        },
        "state": {
          "enrollments": {
            "value": 1311,
            "state": "observed",
            "year": 2025,
            "sourceId": "inep_censo_escolar",
            "sourceField": "QT_MAT_FUND_AI"
          },
          "share": {
            "value": 35.49959382615759,
            "numerator": 1311,
            "denominator": 3693,
            "state": "observed",
            "year": 2025,
            "sourceId": "inep_censo_escolar"
          }
        },
        "federal": {
          "enrollments": {
            "value": 0,
            "state": "derived_zero",
            "year": 2025,
            "sourceId": "inep_censo_escolar",
            "sourceField": "QT_MAT_FUND_AI"
          },
          "share": {
            "value": 0.0,
            "numerator": 0,
            "denominator": 3693,
            "state": "derived_zero",
            "year": 2025,
            "sourceId": "inep_censo_escolar"
          }
        },
        "private": {
          "enrollments": {
            "value": 356,
            "state": "observed",
            "year": 2025,
            "sourceId": "inep_censo_escolar",
            "sourceField": "QT_MAT_FUND_AI"
          },
          "share": {
            "value": 9.639859193067966,
            "numerator": 356,
            "denominator": 3693,
            "state": "observed",
            "year": 2025,
            "sourceId": "inep_censo_escolar"
          }
        }
      },
      "bySchoolLocation": {
        "urban": {
          "enrollments": {
            "value": 3371,
            "state": "observed",
            "year": 2025,
            "sourceId": "inep_censo_escolar",
            "sourceField": "QT_MAT_FUND_AI"
          },
          "share": {
            "value": 91.28080151638235,
            "numerator": 3371,
            "denominator": 3693,
            "state": "observed",
            "year": 2025,
            "sourceId": "inep_censo_escolar"
          }
        },
        "rural": {
          "enrollments": {
            "value": 322,
            "state": "observed",
            "year": 2025,
            "sourceId": "inep_censo_escolar",
            "sourceField": "QT_MAT_FUND_AI"
          },
          "share": {
            "value": 8.719198483617655,
            "numerator": 322,
            "denominator": 3693,
            "state": "observed",
            "year": 2025,
            "sourceId": "inep_censo_escolar"
          }
        }
      },
      "shareOfParentStage": {
        "value": 57.238065716057044,
        "numerator": 3693,
        "denominator": 6452,
        "state": "observed",
        "year": 2025,
        "sourceId": "inep_censo_escolar"
      }
    },
    "finalYears": {
      "total": {
        "value": 2759,
        "state": "observed",
        "year": 2025,
        "sourceId": "inep_censo_escolar",
        "sourceField": "QT_MAT_FUND_AF"
      },
      "shareOfBasicEducation": {
        "value": 24.89847486688927,
        "numerator": 2759,
        "denominator": 11081,
        "state": "observed",
        "year": 2025,
        "sourceId": "inep_censo_escolar"
      },
      "byNetwork": {
        "publicSubtotal": {
          "enrollments": {
            "value": 2507,
            "state": "observed",
            "year": 2025,
            "sourceId": "inep_censo_escolar",
            "sourceField": "derived:municipal+estadual+federal"
          },
          "share": {
            "value": 90.86625588981515,
            "numerator": 2507,
            "denominator": 2759,
            "state": "observed",
            "year": 2025,
            "sourceId": "inep_censo_escolar"
          }
        },
        "municipal": {
          "enrollments": {
            "value": 824,
            "state": "observed",
            "year": 2025,
            "sourceId": "inep_censo_escolar",
            "sourceField": "QT_MAT_FUND_AF"
          },
          "share": {
            "value": 29.865893439652048,
            "numerator": 824,
            "denominator": 2759,
            "state": "observed",
            "year": 2025,
            "sourceId": "inep_censo_escolar"
          }
        },
        "state": {
          "enrollments": {
            "value": 1683,
            "state": "observed",
            "year": 2025,
            "sourceId": "inep_censo_escolar",
            "sourceField": "QT_MAT_FUND_AF"
          },
          "share": {
            "value": 61.0003624501631,
            "numerator": 1683,
            "denominator": 2759,
            "state": "observed",
            "year": 2025,
            "sourceId": "inep_censo_escolar"
          }
        },
        "federal": {
          "enrollments": {
            "value": 0,
            "state": "derived_zero",
            "year": 2025,
            "sourceId": "inep_censo_escolar",
            "sourceField": "QT_MAT_FUND_AF"
          },
          "share": {
            "value": 0.0,
            "numerator": 0,
            "denominator": 2759,
            "state": "derived_zero",
            "year": 2025,
            "sourceId": "inep_censo_escolar"
          }
        },
        "private": {
          "enrollments": {
            "value": 252,
            "state": "observed",
            "year": 2025,
            "sourceId": "inep_censo_escolar",
            "sourceField": "QT_MAT_FUND_AF"
          },
          "share": {
            "value": 9.13374411018485,
            "numerator": 252,
            "denominator": 2759,
            "state": "observed",
            "year": 2025,
            "sourceId": "inep_censo_escolar"
          }
        }
      },
      "bySchoolLocation": {
        "urban": {
          "enrollments": {
            "value": 2536,
            "state": "observed",
            "year": 2025,
            "sourceId": "inep_censo_escolar",
            "sourceField": "QT_MAT_FUND_AF"
          },
          "share": {
            "value": 91.91736136281261,
            "numerator": 2536,
            "denominator": 2759,
            "state": "observed",
            "year": 2025,
            "sourceId": "inep_censo_escolar"
          }
        },
        "rural": {
          "enrollments": {
            "value": 223,
            "state": "observed",
            "year": 2025,
            "sourceId": "inep_censo_escolar",
            "sourceField": "QT_MAT_FUND_AF"
          },
          "share": {
            "value": 8.082638637187387,
            "numerator": 223,
            "denominator": 2759,
            "state": "observed",
            "year": 2025,
            "sourceId": "inep_censo_escolar"
          }
        }
      },
      "shareOfParentStage": {
        "value": 42.76193428394296,
        "numerator": 2759,
        "denominator": 6452,
        "state": "observed",
        "year": 2025,
        "sourceId": "inep_censo_escolar"
      }
    }
  },
  "sources": [
    {
      "id": "inep_censo_escolar_2015",
      "organization": "Instituto Nacional de Estudos e Pesquisas Educacionais Anísio Teixeira (INEP)",
      "title": "Censo Escolar da Educação Básica",
      "referenceYear": 2015,
      "url": "https://www.gov.br/inep/pt-br/acesso-a-informacao/dados-abertos/microdados/censo-escolar"
    },
    {
      "id": "inep_censo_escolar",
      "organization": "Instituto Nacional de Estudos e Pesquisas Educacionais Anísio Teixeira (INEP)",
      "title": "Censo Escolar da Educação Básica",
      "referenceYear": 2025,
      "url": "https://www.gov.br/inep/pt-br/acesso-a-informacao/dados-abertos/microdados/censo-escolar"
    },
    {
      "id": "inep_taxas_rendimento_escolar",
      "organization": "Instituto Nacional de Estudos e Pesquisas Educacionais Anísio Teixeira (INEP)",
      "title": "Taxas de Rendimento Escolar",
      "referenceYear": 2025,
      "url": "https://www.gov.br/inep/pt-br/acesso-a-informacao/dados-abertos/indicadores-educacionais/taxas-de-rendimento-escolar"
    }
  ],
  "methodology": [
    "O snapshot usa exclusivamente o ano de 2025; não há seleção dinâmica nem fallback anual.",
    "Educação Básica usa QT_MAT_BAS como total oficial e não é recomposta pela soma das etapas.",
    "A base territorial é o município onde a escola está localizada; urbana e rural referem-se à localização da escola.",
    "Subtotais públicos só são derivados quando municipal, estadual e federal estão observados ou com zero derivado; ausências não confirmadas permanecem indisponíveis.",
    "Linhas com os sete campos centrais nulos não aumentam totais e mantêm indisponível apenas o recorte de rede/localização afetado.",
    "Zero derivado exige carga municipal completa de 2025, domínios válidos, ausência de duplicidade/negativos, total da etapa observado e ausência de nullCoreRow no recorte.",
    "Os cinco componentes principais da composição reconciliam com QT_MAT_BAS; detalhamentos internos não são somados novamente.",
    "A Educação Especial é um recorte transversal já incluído nas etapas e modalidades da Educação Básica.",
    "As taxas de rendimento usam os registros municipais do INEP para o conjunto das redes, sem média entre escolas ou dependências."
  ],
  "quality": {
    "reconciliations": [
      {
        "id": "early_childhood_substages",
        "label": "Creche + pré-escola = Educação Infantil",
        "expected": 2280,
        "observed": 2280,
        "difference": 0,
        "status": "reconciled"
      },
      {
        "id": "elementary_substages",
        "label": "Anos iniciais + anos finais = Ensino Fundamental",
        "expected": 6452,
        "observed": 6452,
        "difference": 0,
        "status": "reconciled"
      },
      {
        "id": "eja_substages",
        "label": "EJA Fundamental + EJA Médio = EJA",
        "expected": 390,
        "observed": 390,
        "difference": 0,
        "status": "reconciled"
      },
      {
        "id": "special_education_classes",
        "label": "Classes comuns + classes exclusivas = Educação Especial",
        "expected": 962,
        "observed": 962,
        "difference": 0,
        "status": "reconciled"
      },
      {
        "id": "basic_education_composition",
        "label": "Cinco componentes aditivos = Educação Básica",
        "expected": 11081,
        "observed": 11081,
        "difference": 0,
        "status": "reconciled"
      },
      {
        "id": "early_childhood_public_subtotal",
        "label": "Municipal + estadual + federal = subtotal público",
        "expected": 2080,
        "observed": 2080,
        "difference": 0,
        "status": "reconciled"
      },
      {
        "id": "early_childhood_network_total",
        "label": "Subtotal público + privada = total da etapa",
        "expected": 2280,
        "observed": 2280,
        "difference": 0,
        "status": "reconciled"
      },
      {
        "id": "early_childhood_location_total",
        "label": "Urbana + rural = total da etapa",
        "expected": 2280,
        "observed": 2280,
        "difference": 0,
        "status": "reconciled"
      },
      {
        "id": "creche_public_subtotal",
        "label": "Municipal + estadual + federal = subtotal público",
        "expected": 860,
        "observed": 860,
        "difference": 0,
        "status": "reconciled"
      },
      {
        "id": "creche_network_total",
        "label": "Subtotal público + privada = total da etapa",
        "expected": 940,
        "observed": 940,
        "difference": 0,
        "status": "reconciled"
      },
      {
        "id": "creche_location_total",
        "label": "Urbana + rural = total da etapa",
        "expected": 940,
        "observed": 940,
        "difference": 0,
        "status": "reconciled"
      },
      {
        "id": "pre_school_public_subtotal",
        "label": "Municipal + estadual + federal = subtotal público",
        "expected": 1220,
        "observed": 1220,
        "difference": 0,
        "status": "reconciled"
      },
      {
        "id": "pre_school_network_total",
        "label": "Subtotal público + privada = total da etapa",
        "expected": 1340,
        "observed": 1340,
        "difference": 0,
        "status": "reconciled"
      },
      {
        "id": "pre_school_location_total",
        "label": "Urbana + rural = total da etapa",
        "expected": 1340,
        "observed": 1340,
        "difference": 0,
        "status": "reconciled"
      },
      {
        "id": "elementary_public_subtotal",
        "label": "Municipal + estadual + federal = subtotal público",
        "expected": 5844,
        "observed": 5844,
        "difference": 0,
        "status": "reconciled"
      },
      {
        "id": "elementary_network_total",
        "label": "Subtotal público + privada = total da etapa",
        "expected": 6452,
        "observed": 6452,
        "difference": 0,
        "status": "reconciled"
      },
      {
        "id": "elementary_location_total",
        "label": "Urbana + rural = total da etapa",
        "expected": 6452,
        "observed": 6452,
        "difference": 0,
        "status": "reconciled"
      },
      {
        "id": "initial_years_public_subtotal",
        "label": "Municipal + estadual + federal = subtotal público",
        "expected": 3337,
        "observed": 3337,
        "difference": 0,
        "status": "reconciled"
      },
      {
        "id": "initial_years_network_total",
        "label": "Subtotal público + privada = total da etapa",
        "expected": 3693,
        "observed": 3693,
        "difference": 0,
        "status": "reconciled"
      },
      {
        "id": "initial_years_location_total",
        "label": "Urbana + rural = total da etapa",
        "expected": 3693,
        "observed": 3693,
        "difference": 0,
        "status": "reconciled"
      },
      {
        "id": "final_years_public_subtotal",
        "label": "Municipal + estadual + federal = subtotal público",
        "expected": 2507,
        "observed": 2507,
        "difference": 0,
        "status": "reconciled"
      },
      {
        "id": "final_years_network_total",
        "label": "Subtotal público + privada = total da etapa",
        "expected": 2759,
        "observed": 2759,
        "difference": 0,
        "status": "reconciled"
      },
      {
        "id": "final_years_location_total",
        "label": "Urbana + rural = total da etapa",
        "expected": 2759,
        "observed": 2759,
        "difference": 0,
        "status": "reconciled"
      },
      {
        "id": "high_school_public_subtotal",
        "label": "Municipal + estadual + federal = subtotal público",
        "expected": 1665,
        "observed": 1665,
        "difference": 0,
        "status": "reconciled"
      },
      {
        "id": "high_school_network_total",
        "label": "Subtotal público + privada = total da etapa",
        "expected": 1746,
        "observed": 1746,
        "difference": 0,
        "status": "reconciled"
      },
      {
        "id": "high_school_location_total",
        "label": "Urbana + rural = total da etapa",
        "expected": 1746,
        "observed": 1746,
        "difference": 0,
        "status": "reconciled"
      }
    ],
    "semanticWarnings": [],
    "nullCoreRows": [],
    "completeness": {
      "referenceYear": 2025,
      "expectedMunicipalities": 497,
      "municipalitiesPresent": 497,
      "annualLoadPresent": true,
      "validDependencyDomain": true,
      "validSchoolLocationDomain": true,
      "duplicateGrainCount": 0,
      "negativeValueCount": 0,
      "isCompleteForDerivedZero": true
    },
    "schoolPerformanceChecks": [
      {
        "stage": "elementary",
        "sum": 100.0,
        "difference": 0.0,
        "status": "reconciled"
      },
      {
        "stage": "initialYears",
        "sum": 100.0,
        "difference": 0.0,
        "status": "reconciled"
      },
      {
        "stage": "finalYears",
        "sum": 100.0,
        "difference": 0.0,
        "status": "reconciled"
      },
      {
        "stage": "highSchool",
        "sum": 100.0,
        "difference": 0.0,
        "status": "reconciled"
      }
    ]
  }
}
